uim/__init__.py
uim/codec/__init__.py
uim/codec/base.py
uim/codec/context/__init__.py
uim/codec/context/decoder.py
uim/codec/context/encoder.py
uim/codec/context/scheme.py
uim/codec/context/version.py
uim/codec/format/UIM_3_0_0_pb2.py
uim/codec/format/UIM_3_1_0_pb2.py
uim/codec/format/WILL_2_0_0_pb2.py
uim/codec/format/__init__.py
uim/codec/parser/__init__.py
uim/codec/parser/base.py
uim/codec/parser/inkml.py
uim/codec/parser/iotpaper.py
uim/codec/parser/uim.py
uim/codec/parser/will.py
uim/codec/parser/decoder/__init__.py
uim/codec/parser/decoder/base.py
uim/codec/parser/decoder/decoder_3_0_0.py
uim/codec/parser/decoder/decoder_3_1_0.py
uim/codec/writer/__init__.py
uim/codec/writer/encoder/__init__.py
uim/codec/writer/encoder/base.py
uim/codec/writer/encoder/encoder_3_1_0.py
uim/model/__init__.py
uim/model/base.py
uim/model/ink.py
uim/model/helpers/__init__.py
uim/model/helpers/boundingbox.py
uim/model/helpers/policy.py
uim/model/helpers/schema_content_extractor.py
uim/model/helpers/serialize.py
uim/model/helpers/spline.py
uim/model/helpers/text_extractor.py
uim/model/helpers/treeiterator.py
uim/model/inkdata/__init__.py
uim/model/inkdata/brush.py
uim/model/inkdata/strokes.py
uim/model/inkinput/__init__.py
uim/model/inkinput/inputdata.py
uim/model/inkinput/sensordata.py
uim/model/semantics/__init__.py
uim/model/semantics/node.py
uim/model/semantics/schema.py
uim/model/semantics/structures.py
uim/utils/__init__.py
uim/utils/analyser.py
uim/utils/matrix.py
uim/utils/print.py
uim/utils/statistics.py
uim/utils/stroke_resampling.py
universal_ink_library-2.1.1.dist-info/LICENSE
universal_ink_library-2.1.1.dist-info/METADATA
universal_ink_library-2.1.1.dist-info/WHEEL
universal_ink_library-2.1.1.dist-info/top_level.txt
universal_ink_library-2.1.1.dist-info/RECORD
