Metadata-Version: 2.1
Name: universal-ink-library
Version: 2.1.1
Summary: Library to parse and write Universal Ink Model data files.
Home-page: https://github.com/Wacom-Developer/universal-ink-library
Author: Markus Weber
Author-email: markus.weber@wacom.com
License: Apache 2.0 License
Keywords: universal ink model;digital ink;wacom ink technologies
Platform: UNKNOWN
Classifier: Development Status :: 4 - Beta
Classifier: Intended Audience :: Developers
Classifier: Intended Audience :: Education
Classifier: Intended Audience :: Science/Research
Classifier: Programming Language :: Python :: 3
Classifier: Programming Language :: Python :: 3.9
Classifier: Programming Language :: Python :: 3.10
Classifier: Programming Language :: Python :: 3.11
Classifier: Programming Language :: Python :: 3.12
Classifier: Programming Language :: Python :: 3.13
Classifier: Topic :: File Formats
Classifier: Topic :: Utilities
License-File: LICENSE
Requires-Dist: numpy>=1.16.4
Requires-Dist: bitstring>=3.1.7
Requires-Dist: protobuf<4.0.0
Requires-Dist: varint>=1.0.2
Requires-Dist: lxml>=4.6.3
Requires-Dist: python-dateutil==2.9.0
